{
  "header": {
    "gtfs_realtime_version": "1.0",
    "incrementality": 0
  },
  "entity": [
    {
      "id": "1",
      "alert": {
        "informed_entity": [
          {
            "agency_id": "SydneyTrains",
            "trip": {
              "trip_id": "92-P.1241.120.64.A.8.63618940"
            }
          },
          {
            "agency_id": "SydneyTrains",
            "trip": {
              "trip_id": "21-P.1241.120.120.B.8.63623820"
            }
          },
          {
            "agency_id": "SydneyTrains",
            "trip": {
              "trip_id": "67-P.1241.120.64.M.8.63618427"
            }
          }
        ],
        "url": {
          "translation": [
            {
              "text": "https://transportnsw.info/alerts#/train",
              "language": "en"
            }
          ]
        },
        "header_text": {
          "translation": [
            {
              "text": "Delayed",
              "language": "en"
            }
          ]
        },
        "description_text": {
          "translation": [
            {
              "text": " due to a train requiring mechanical repairs at Strathfield earlier. Please listen to announcements and check transport apps for your next service.",
              "language": "en"
            }
          ]
        }
      }
    },
    {
      "id": "3",
      "alert": {
        "informed_entity": [
          {
            "agency_id": "SydneyTrains",
            "trip": {
              "trip_id": "W581.1241.120.64.V.4.63798030"
            }
          },
          {
            "agency_id": "SydneyTrains",
            "trip": {
              "trip_id": "W583.1241.120.64.V.4.63618431"
            }
          },
          {
            "agency_id": "SydneyTrains",
            "trip": {
              "trip_id": "W587.1241.120.64.V.4.63618935"
            }
          }
        ],
        "url": {
          "translation": [
            {
              "text": "https://transportnsw.info/alerts#/train",
              "language": "en"
            }
          ]
        },
        "header_text": {
          "translation": [
            {
              "text": "Delayed",
              "language": "en"
            }
          ]
        },
        "description_text": {
          "translation": [
            {
              "text": " due to trains requiring mechanical repairs at Central and Strathfield earlier.  Please allow 10- 20 minutes additional travel time.",
              "language": "en"
            }
          ]
        }
      }
    },
    {
      "id": "4",
      "alert": {
        "informed_entity": [
          {
            "agency_id": "SydneyTrains",
            "trip": {
              "trip_id": "131G.1241.120.124.A.8.63621118"
            }
          }
        ],
        "url": {
          "translation": [
            {
              "text": "https://transportnsw.info/alerts#/train",
              "language": "en"
            }
          ]
        },
        "header_text": {
          "translation": [
            {
              "text": "Delayed",
              "language": "en"
            }
          ]
        },
        "description_text": {
          "translation": [
            {
              "text": " due to a train requiring mechanical repairs at Parramatta earlier.",
              "language": "en"
            }
          ]
        }
      }
    },
    {
      "id": "5",
      "alert": {
        "informed_entity": [
          {
            "agency_id": "SydneyTrains",
            "trip": {
              "trip_id": "144U.1241.120.64.A.8.63618194"
            }
          }
        ],
        "url": {
          "translation": [
            {
              "text": "https://transportnsw.info/alerts#/train",
              "language": "en"
            }
          ]
        },
        "header_text": {
          "translation": [
            {
              "text": "Delayed",
              "language": "en"
            }
          ]
        },
        "description_text": {
          "translation": [
            {
              "text": " due to a train requiring mechanical repairs at Strathfield earlier. Please allow additional travel time of 5-10 minutes.",
              "language": "en"
            }
          ]
        }
      }
    },
    {
      "id": "7",
      "alert": {
        "informed_entity": [
          {
            "agency_id": "SydneyTrains",
            "trip": {
              "trip_id": "130R.1241.120.64.A.8.63618623"
            }
          },
          {
            "agency_id": "SydneyTrains",
            "trip": {
              "trip_id": "121T.1241.120.64.A.8.63798554"
            }
          },
          {
            "agency_id": "SydneyTrains",
            "trip": {
              "trip_id": "160R.1241.120.64.A.8.63621636"
            }
          },
          {
            "agency_id": "SydneyTrains",
            "trip": {
              "trip_id": "152L.1241.120.100.A.8.63622769"
            }
          }
        ],
        "url": {
          "translation": [
            {
              "text": "https://transportnsw.info/alerts#/train",
              "language": "en"
            }
          ]
        },
        "header_text": {
          "translation": [
            {
              "text": "Delayed",
              "language": "en"
            }
          ]
        },
        "description_text": {
          "translation": [
            {
              "text": " due to a train requiring mechanical repairs at Strathfield earlier. Please allow additional travel time of up to 10 minutes.",
              "language": "en"
            }
          ]
        }
      }
    },
    {
      "id": "8",
      "alert": {
        "informed_entity": [
          {
            "agency_id": "SydneyTrains",
            "trip": {
              "trip_id": "130R.1241.120.64.A.8.63618623"
            }
          }
        ],
        "url": {
          "translation": [
            {
              "text": "https://transportnsw.info/alerts#/train",
              "language": "en"
            }
          ]
        },
        "header_text": {
          "translation": [
            {
              "text": "Not stopping at",
              "language": "en"
            }
          ]
        },
        "description_text": {
          "translation": [
            {
              "text": "Seven Hills, Westmead, Lidcombe due to a train requiring mechanical repairs at Strathfield earlier. Please allow additional travel time of up to 10 minutes.",
              "language": "en"
            }
          ]
        }
      }
    },
    {
      "id": "9",
      "alert": {
        "informed_entity": [
          {
            "agency_id": "SydneyTrains",
            "trip": {
              "trip_id": "SN71.1241.120.64.N.2.63618554"
            }
          }
        ],
        "url": {
          "translation": [
            {
              "text": "https://transportnsw.info/alerts#/train",
              "language": "en"
            }
          ]
        },
        "header_text": {
          "translation": [
            {
              "text": "Delayed",
              "language": "en"
            }
          ]
        },
        "description_text": {
          "translation": [
            {
              "text": " due to an operational issue earlier",
              "language": "en"
            }
          ]
        }
      }
    },
    {
      "id": "12",
      "alert": {
        "informed_entity": [
          {
            "agency_id": "SydneyTrains",
            "trip": {
              "trip_id": "V682.1241.120.64.N.2.63622967"
            }
          }
        ],
        "url": {
          "translation": [
            {
              "text": "https://transportnsw.info/alerts#/train",
              "language": "en"
            }
          ]
        },
        "header_text": {
          "translation": [
            {
              "text": "Commencing from",
              "language": "en"
            }
          ]
        },
        "description_text": {
          "translation": [
            {
              "text": "Singleton due to track equipment repairs at Singleton.   A replacement bus service will operate all stations between Scone and Singleton. Please allow additional travel time.",
              "language": "en"
            }
          ]
        }
      }
    },
    {
      "id": "13",
      "alert": {
        "informed_entity": [
          {
            "agency_id": "SydneyTrains",
            "trip": {
              "trip_id": "22-Y.1241.120.104.B.8.63618404"
            }
          },
          {
            "agency_id": "SydneyTrains",
            "trip": {
              "trip_id": "22XW.1241.120.104.B.8.63618406"
            }
          }
        ],
        "url": {
          "translation": [
            {
              "text": "https://transportnsw.info/alerts#/train",
              "language": "en"
            }
          ]
        },
        "header_text": {
          "translation": [
            {
              "text": "General update",
              "language": "en"
            }
          ]
        },
        "description_text": {
          "translation": [
            {
              "text": " The 5th carriage from the front of this train is unavailable. Please move along the platform to board another available carriage.",
              "language": "en"
            }
          ]
        }
      }
    },
    {
      "id": "15",
      "alert": {
        "informed_entity": [
          {
            "agency_id": "SydneyTrains",
            "trip": {
              "trip_id": "V679.1241.120.64.N.2.63621423"
            }
          }
        ],
        "url": {
          "translation": [
            {
              "text": "https://transportnsw.info/alerts#/train",
              "language": "en"
            }
          ]
        },
        "header_text": {
          "translation": [
            {
              "text": "Now terminating at",
              "language": "en"
            }
          ]
        },
        "description_text": {
          "translation": [
            {
              "text": "Singleton due to track equipment repairs at Singleton.  A replacement bus service will operate all stations between Singleton and Scone. Please allow additional travel time.",
              "language": "en"
            }
          ]
        }
      }
    },
    {
      "id": "16",
      "alert": {
        "informed_entity": [
          {
            "agency_id": "SydneyTrains",
            "trip": {
              "trip_id": "130T.1241.120.64.A.8.63621625"
            }
          }
        ],
        "url": {
          "translation": [
            {
              "text": "https://transportnsw.info/alerts#/train",
              "language": "en"
            }
          ]
        },
        "header_text": {
          "translation": [
            {
              "text": "Commencing from",
              "language": "en"
            }
          ]
        },
        "description_text": {
          "translation": [
            {
              "text": "North Sydney due to a train requiring mechanical repairs at Strathfield earlier.",
              "language": "en"
            }
          ]
        }
      }
    },
    {
      "id": "17",
      "alert": {
        "informed_entity": [
          {
            "agency_id": "SydneyTrains",
            "trip": {
              "trip_id": "121V.1241.120.64.A.8.63623525"
            }
          }
        ],
        "url": {
          "translation": [
            {
              "text": "https://transportnsw.info/alerts#/train",
              "language": "en"
            }
          ]
        },
        "header_text": {
          "translation": [
            {
              "text": "Commencing from",
              "language": "en"
            }
          ]
        },
        "description_text": {
          "translation": [
            {
              "text": "Lindfield due to a train requiring mechanical repairs at Strathfield earlier.",
              "language": "en"
            }
          ]
        }
      }
    },
    {
      "id": "19",
      "alert": {
        "informed_entity": [
          {
            "agency_id": "SydneyTrains",
            "trip": {
              "trip_id": "121U.1241.120.64.A.8.63798555"
            }
          },
          {
            "agency_id": "SydneyTrains",
            "trip": {
              "trip_id": "130S.1241.120.64.A.8.63621624"
            }
          }
        ],
        "url": {
          "translation": [
            {
              "text": "https://transportnsw.info/alerts#/train",
              "language": "en"
            }
          ]
        },
        "header_text": {
          "translation": [
            {
              "text": "Delayed",
              "language": "en"
            }
          ]
        },
        "description_text": {
          "translation": [
            {
              "text": " due to a train requiring mechanical repairs at Strathfield earlier.",
              "language": "en"
            }
          ]
        }
      }
    },
    {
      "id": "20",
      "alert": {
        "informed_entity": [
          {
            "agency_id": "SydneyTrains",
            "trip": {
              "trip_id": "121U.1241.120.64.A.8.63798555"
            }
          }
        ],
        "url": {
          "translation": [
            {
              "text": "https://transportnsw.info/alerts#/train",
              "language": "en"
            }
          ]
        },
        "header_text": {
          "translation": [
            {
              "text": "Now terminating at",
              "language": "en"
            }
          ]
        },
        "description_text": {
          "translation": [
            {
              "text": "Lindfield due to a train requiring mechanical repairs at Strathfield earlier.",
              "language": "en"
            }
          ]
        }
      }
    },
    {
      "id": "21",
      "alert": {
        "informed_entity": [
          {
            "agency_id": "SydneyTrains",
            "trip": {
              "trip_id": "V676.1241.120.124.J.2.63621869"
            }
          }
        ],
        "url": {
          "translation": [
            {
              "text": "https://transportnsw.info/alerts#/train",
              "language": "en"
            }
          ]
        },
        "header_text": {
          "translation": [
            {
              "text": "Delayed",
              "language": "en"
            }
          ]
        },
        "description_text": {
          "translation": [
            {
              "text": " due to track equipment repairs at Singleton. This train is running approximately 15 minutes behind schedule. A replacement bus service will operate between Scone and Singleton (one express bus will run direct from Scone to Maitland and one bus will run Scone, all stations to Singleton. Please allow additional travel time.",
              "language": "en"
            }
          ]
        }
      }
    },
    {
      "id": "22",
      "alert": {
        "informed_entity": [
          {
            "agency_id": "SydneyTrains",
            "trip": {
              "trip_id": "V676.1241.120.124.J.2.63621869"
            }
          }
        ],
        "url": {
          "translation": [
            {
              "text": "https://transportnsw.info/alerts#/train",
              "language": "en"
            }
          ]
        },
        "header_text": {
          "translation": [
            {
              "text": "Commencing from",
              "language": "en"
            }
          ]
        },
        "description_text": {
          "translation": [
            {
              "text": "Singleton due to track equipment repairs at Singleton. This train is running approximately 15 minutes behind schedule. A replacement bus service will operate between Scone and Singleton (one express bus will run direct from Scone to Maitland and one bus will run Scone, all stations to Singleton. Please allow additional travel time.",
              "language": "en"
            }
          ]
        }
      }
    },
    {
      "id": "24",
      "alert": {
        "informed_entity": [
          {
            "agency_id": "SydneyTrains",
            "trip": {
              "trip_id": "130S.1241.120.64.A.8.63621624"
            }
          }
        ],
        "url": {
          "translation": [
            {
              "text": "https://transportnsw.info/alerts#/train",
              "language": "en"
            }
          ]
        },
        "header_text": {
          "translation": [
            {
              "text": "General update",
              "language": "en"
            }
          ]
        },
        "description_text": {
          "translation": [
            {
              "text": " No access to the 1st carriage due to an act of vandalism. Please board adjacent carriages.",
              "language": "en"
            }
          ]
        }
      }
    },
    {
      "id": "25",
      "alert": {
        "informed_entity": [
          {
            "agency_id": "SydneyTrains",
            "trip": {
              "trip_id": "130S.1241.120.64.A.8.63621624"
            }
          }
        ],
        "url": {
          "translation": [
            {
              "text": "https://transportnsw.info/alerts#/train",
              "language": "en"
            }
          ]
        },
        "header_text": {
          "translation": [
            {
              "text": "Now terminating at",
              "language": "en"
            }
          ]
        },
        "description_text": {
          "translation": [
            {
              "text": "North Sydney due to a train requiring mechanical repairs at Strathfield earlier.",
              "language": "en"
            }
          ]
        }
      }
    },
    {
      "id": "27",
      "alert": {
        "informed_entity": [
          {
            "agency_id": "SydneyTrains",
            "trip": {
              "trip_id": "SN69.1241.120.124.N.2.63620645"
            }
          }
        ],
        "url": {
          "translation": [
            {
              "text": "https://transportnsw.info/alerts#/train",
              "language": "en"
            }
          ]
        },
        "header_text": {
          "translation": [
            {
              "text": "Cancelled",
              "language": "en"
            }
          ]
        },
        "description_text": {
          "translation": [
            {
              "text": " This train is cancelled due to a train requiring mechanical repairs earlier. A replacement bus service between Campbelltown & Moss Vale has been provided & will depart Campbelltown at approximately 7.20pm. Please allow additional travel time.",
              "language": "en"
            }
          ]
        }
      }
    },
    {
      "id": "29",
      "alert": {
        "informed_entity": [
          {
            "agency_id": "SydneyTrains",
            "stop_id": "200060"
          }
        ],
        "cause": 2,
        "effect": 8,
        "url": {
          "translation": [
            {
              "text": "https://transportnsw.info/alerts#/train",
              "language": "en"
            }
          ]
        },
        "header_text": {
          "translation": [
            {
              "text": "Escalator Availability - Central",
              "language": "en"
            }
          ]
        },
        "description_text": {
          "translation": [
            {
              "text": "From 18 October to mid-December 2020, the north escalator from the concourse to Platforms 24 and 25 (Town Hall end) will be temporarily closed for maintenance works. To access platforms 24 and 25 travel down the concourse to the lift or use the south escalator to Platforms 24 and 25 (Redfern end). You can view a map of the station here https://transportnsw.info/document/4930/central-station-map.pdf. If you need assistance, see station staff or phone 9379 1777.",
              "language": "en"
            }
          ]
        }
      }
    },
    {
      "id": "30",
      "alert": {
        "informed_entity": [
          {
            "agency_id": "SydneyTrains",
            "stop_id": "206710"
          }
        ],
        "cause": 2,
        "effect": 8,
        "url": {
          "translation": [
            {
              "text": "https://transportnsw.info/alerts#/train",
              "language": "en"
            }
          ]
        },
        "header_text": {
          "translation": [
            {
              "text": "Lift Availability - Chatswood",
              "language": "en"
            }
          ]
        },
        "description_text": {
          "translation": [
            {
              "text": "The lift between the concourse and platforms 1/2 is temporarily out of service. If you require assistance, please ask staff or call 9379 3311.",
              "language": "en"
            }
          ]
        }
      }
    },
    {
      "id": "31",
      "alert": {
        "informed_entity": [
          {
            "agency_id": "SydneyTrains",
            "stop_id": "212110"
          }
        ],
        "cause": 2,
        "effect": 8,
        "url": {
          "translation": [
            {
              "text": "https://transportnsw.info/alerts#/train",
              "language": "en"
            }
          ]
        },
        "header_text": {
          "translation": [
            {
              "text": "Lift Availability - Epping",
              "language": "en"
            }
          ]
        },
        "description_text": {
          "translation": [
            {
              "text": "The lift between the footbridge and Beecroft Road is temporarily out of service. If you require assistance, please ask staff or call 8878 4100.",
              "language": "en"
            }
          ]
        }
      }
    },
    {
      "id": "32",
      "alert": {
        "informed_entity": [
          {
            "agency_id": "SydneyTrains",
            "stop_id": "214710"
          }
        ],
        "cause": 2,
        "effect": 8,
        "url": {
          "translation": [
            {
              "text": "https://transportnsw.info/alerts#/train",
              "language": "en"
            }
          ]
        },
        "header_text": {
          "translation": [
            {
              "text": "Lift Availability - Seven Hills",
              "language": "en"
            }
          ]
        },
        "description_text": {
          "translation": [
            {
              "text": "The lift between the concourse and Boomerang Place is temporarily out of service. If you require assistance, please ask staff or phone 9851 7431.",
              "language": "en"
            }
          ]
        }
      }
    },
    {
      "id": "33",
      "alert": {
        "informed_entity": [
          {
            "agency_id": "SydneyTrains",
            "stop_id": "215020"
          }
        ],
        "cause": 2,
        "effect": 8,
        "url": {
          "translation": [
            {
              "text": "https://transportnsw.info/alerts#/train",
              "language": "en"
            }
          ]
        },
        "header_text": {
          "translation": [
            {
              "text": "Lift Availability - Parramatta",
              "language": "en"
            }
          ]
        },
        "description_text": {
          "translation": [
            {
              "text": "The lift between platform 1 and the western concourse is temporarily out of service. If you require assistance, ask staff or phone 9848 9450.",
              "language": "en"
            }
          ]
        }
      }
    },
    {
      "id": "34",
      "alert": {
        "informed_entity": [
          {
            "agency_id": "SydneyTrains",
            "stop_id": "221620"
          }
        ],
        "cause": 2,
        "effect": 8,
        "url": {
          "translation": [
            {
              "text": "https://transportnsw.info/alerts#/train",
              "language": "en"
            }
          ]
        },
        "header_text": {
          "translation": [
            {
              "text": "Lift Availability - Rockdale",
              "language": "en"
            }
          ]
        },
        "description_text": {
          "translation": [
            {
              "text": "The lift between the concourse and the Princes Highway is temporarily out of service. For assistance ask staff or call 9563 7574.",
              "language": "en"
            }
          ]
        }
      }
    },
    {
      "id": "35",
      "alert": {
        "informed_entity": [
          {
            "agency_id": "SydneyTrains",
            "stop_id": "251550"
          }
        ],
        "cause": 2,
        "effect": 8,
        "url": {
          "translation": [
            {
              "text": "https://transportnsw.info/alerts#/train",
              "language": "en"
            }
          ]
        },
        "header_text": {
          "translation": [
            {
              "text": "Lift Availability - Thirroul",
              "language": "en"
            }
          ]
        },
        "description_text": {
          "translation": [
            {
              "text": "The lift between platform 1 and Railway Pde is temporarily out of service. If you require assistance, please ask staff or phone 4223 5576.",
              "language": "en"
            }
          ]
        }
      }
    },
    {
      "id": "36",
      "alert": {
        "informed_entity": [
          {
            "agency_id": "SydneyTrains",
            "stop_id": "200060"
          }
        ],
        "cause": 2,
        "effect": 8,
        "url": {
          "translation": [
            {
              "text": "https://transportnsw.info/alerts#/train",
              "language": "en"
            }
          ]
        },
        "header_text": {
          "translation": [
            {
              "text": "Station Update - Central",
              "language": "en"
            }
          ]
        },
        "description_text": {
          "translation": [
            {
              "text": "There are changes happening at Central Station due to Sydney Metro construction works. Access to certain areas of the station and platforms may be limited, which means using different stairs, escalators and lifts. Please follow the signs and staff directions. If you need assistance, see station staff. For detailed information please visit https://transportnsw.info/alerts/details#/6049959",
              "language": "en"
            }
          ]
        }
      }
    },
    {
      "id": "37",
      "alert": {
        "informed_entity": [
          {
            "agency_id": "SydneyTrains",
            "stop_id": "222610"
          }
        ],
        "cause": 2,
        "effect": 8,
        "url": {
          "translation": [
            {
              "text": "https://transportnsw.info/alerts#/train",
              "language": "en"
            }
          ]
        },
        "header_text": {
          "translation": [
            {
              "text": "Station Update - Como",
              "language": "en"
            }
          ]
        },
        "description_text": {
          "translation": [
            {
              "text": "Access to and from Como Station from Railway Road is currently unavailable whilst a station upgrade is in progress. During this time, please enter and exit the station via Como Parade.",
              "language": "en"
            }
          ]
        }
      }
    },
    {
      "id": "38",
      "alert": {
        "informed_entity": [
          {
            "agency_id": "SydneyTrains",
            "stop_id": "222010"
          }
        ],
        "cause": 2,
        "effect": 8,
        "url": {
          "translation": [
            {
              "text": "https://transportnsw.info/alerts#/train",
              "language": "en"
            }
          ]
        },
        "header_text": {
          "translation": [
            {
              "text": "Station Update - Hurstville",
              "language": "en"
            }
          ]
        },
        "description_text": {
          "translation": [
            {
              "text": "Due to station upgrade works installing additional Opal gates, the wide access gate on the Eastern side of the concourse will be temporarily closed from 18 September until mid November. Please use the new wide access gate available on the Western side of the concourse. Please follow the signs or see Station Staff for assistance.",
              "language": "en"
            }
          ]
        }
      }
    },
    {
      "id": "39",
      "alert": {
        "informed_entity": [
          {
            "agency_id": "SydneyTrains",
            "stop_id": "204420"
          }
        ],
        "cause": 2,
        "effect": 8,
        "url": {
          "translation": [
            {
              "text": "https://transportnsw.info/alerts#/train",
              "language": "en"
            }
          ]
        },
        "header_text": {
          "translation": [
            {
              "text": "Station Update - Sydenham",
              "language": "en"
            }
          ]
        },
        "description_text": {
          "translation": [
            {
              "text": "New Metro Platforms are being constructed on platforms 1 & 2 at Sydenham Station. T3 Bankstown Line services to the City operate from platform 3 & T3 Bankstown Line services to Lidcombe and Liverpool operate from platform 4. Platform 4, 5 & 6 upgrade works - A new Metro concourse is also being constructed at the Northern end of the station. While the concourse is being installed, please board and alight from the first 5 carriages of the train on platforms 4 & 6 and the last 6 carriages of the train on platform 5. If you need help, please see staff at the station. For more information on these upgrades, please see sydneymetro.info",
              "language": "en"
            }
          ]
        }
      }
    }
  ]
}