{
  "header": {
    "gtfs_realtime_version": "1.0",
    "incrementality": 0
  },
  "entity": [
    {
      "id": "1",
      "alert": {
        "informed_entity": [
          {
            "agency_id": "SydneyTrains",
            "trip": {
              "trip_id": "603G.1479.128.32.T.8.64086443"
            }
          },
          {
            "agency_id": "SydneyTrains",
            "trip": {
              "trip_id": "603H.1479.128.32.T.8.64088998"
            }
          }
        ],
        "url": {
          "translation": [
            {
              "text": "https://transportnsw.info/alerts#/train",
              "language": "en"
            }
          ]
        },
        "header_text": {
          "translation": [
            {
              "text": "Cancelled",
              "language": "en"
            }
          ]
        },
        "description_text": {
          "translation": [
            {
              "text": " Due to a medical emergency at Central earlier. Please allow additional travel time.",
              "language": "en"
            }
          ]
        }
      }
    },
    {
      "id": "2",
      "alert": {
        "informed_entity": [
          {
            "agency_id": "SydneyTrains",
            "trip": {
              "trip_id": "W558.1479.128.32.V.4.64087596"
            }
          }
        ],
        "url": {
          "translation": [
            {
              "text": "https://transportnsw.info/alerts#/train",
              "language": "en"
            }
          ]
        },
        "header_text": {
          "translation": [
            {
              "text": "Cancelled",
              "language": "en"
            }
          ]
        },
        "description_text": {
          "translation": [
            {
              "text": " due to a train requiring mechanical repairs at Parramatta",
              "language": "en"
            }
          ]
        }
      }
    },
    {
      "id": "3",
      "alert": {
        "informed_entity": [
          {
            "agency_id": "SydneyTrains",
            "trip": {
              "trip_id": "W573.1479.128.32.V.8.64087600"
            }
          }
        ],
        "url": {
          "translation": [
            {
              "text": "https://transportnsw.info/alerts#/train",
              "language": "en"
            }
          ]
        },
        "header_text": {
          "translation": [
            {
              "text": "General update",
              "language": "en"
            }
          ]
        },
        "description_text": {
          "translation": [
            {
              "text": " This service for today only will be 4 carriages due to a mechanical issue earlier.  Please be in the correct area for getting on and off this service.",
              "language": "en"
            }
          ]
        }
      }
    },
    {
      "id": "4",
      "alert": {
        "informed_entity": [
          {
            "agency_id": "SydneyTrains",
            "trip": {
              "trip_id": "C159.1479.128.48.H.8.64086422"
            }
          },
          {
            "agency_id": "SydneyTrains",
            "trip": {
              "trip_id": "C160.1479.128.40.H.4.64084240"
            }
          },
          {
            "agency_id": "SydneyTrains",
            "trip": {
              "trip_id": "C359.1479.128.124.T.4.64087185"
            }
          }
        ],
        "url": {
          "translation": [
            {
              "text": "https://transportnsw.info/alerts#/train",
              "language": "en"
            }
          ]
        },
        "header_text": {
          "translation": [
            {
              "text": "Delayed",
              "language": "en"
            }
          ]
        },
        "description_text": {
          "translation": [
            {
              "text": " Due to a medical emergency at Central earlier. Please allow additional travel time.",
              "language": "en"
            }
          ]
        }
      }
    },
    {
      "id": "5",
      "alert": {
        "informed_entity": [
          {
            "agency_id": "SydneyTrains",
            "trip": {
              "trip_id": "N162.1479.128.100.V.8.64086203"
            }
          }
        ],
        "url": {
          "translation": [
            {
              "text": "https://transportnsw.info/alerts#/train",
              "language": "en"
            }
          ]
        },
        "header_text": {
          "translation": [
            {
              "text": "Delayed",
              "language": "en"
            }
          ]
        },
        "description_text": {
          "translation": [
            {
              "text": " due to an earlier operational issue.",
              "language": "en"
            }
          ]
        }
      }
    },
    {
      "id": "6",
      "alert": {
        "informed_entity": [
          {
            "agency_id": "SydneyTrains",
            "trip": {
              "trip_id": "3--U.1479.128.48.B.8.64086300"
            }
          },
          {
            "agency_id": "SydneyTrains",
            "trip": {
              "trip_id": "3--N.1479.128.48.B.8.64084104"
            }
          },
          {
            "agency_id": "SydneyTrains",
            "trip": {
              "trip_id": "3--V.1479.128.48.B.8.64415294"
            }
          },
          {
            "agency_id": "SydneyTrains",
            "trip": {
              "trip_id": "3--T.1479.128.48.B.8.64086299"
            }
          }
        ],
        "url": {
          "translation": [
            {
              "text": "https://transportnsw.info/alerts#/train",
              "language": "en"
            }
          ]
        },
        "header_text": {
          "translation": [
            {
              "text": "General update",
              "language": "en"
            }
          ]
        },
        "description_text": {
          "translation": [
            {
              "text": " The 7th carriage is unavailable due to a mechanical issue.  Please move along the platform to board one of the other carriages of this service.",
              "language": "en"
            }
          ]
        }
      }
    },
    {
      "id": "7",
      "alert": {
        "informed_entity": [
          {
            "agency_id": "SydneyTrains",
            "trip": {
              "trip_id": "16-R.1479.128.56.B.8.64088161"
            }
          },
          {
            "agency_id": "SydneyTrains",
            "trip": {
              "trip_id": "16-S.1479.128.56.B.8.64088162"
            }
          },
          {
            "agency_id": "SydneyTrains",
            "trip": {
              "trip_id": "16-V.1479.128.56.B.8.64087983"
            }
          },
          {
            "agency_id": "SydneyTrains",
            "trip": {
              "trip_id": "16-W.1479.128.56.B.8.64088702"
            }
          }
        ],
        "url": {
          "translation": [
            {
              "text": "https://transportnsw.info/alerts#/train",
              "language": "en"
            }
          ]
        },
        "header_text": {
          "translation": [
            {
              "text": "General update",
              "language": "en"
            }
          ]
        },
        "description_text": {
          "translation": [
            {
              "text": " The 7th carriage is unavailable. Please move along the platform to board one of the other carriages of this service.",
              "language": "en"
            }
          ]
        }
      }
    },
    {
      "id": "9",
      "alert": {
        "informed_entity": [
          {
            "agency_id": "SydneyTrains",
            "trip": {
              "trip_id": "91-L.1479.128.56.A.8.64087297"
            }
          }
        ],
        "url": {
          "translation": [
            {
              "text": "https://transportnsw.info/alerts#/train",
              "language": "en"
            }
          ]
        },
        "header_text": {
          "translation": [
            {
              "text": "Delayed",
              "language": "en"
            }
          ]
        },
        "description_text": {
          "translation": [
            {
              "text": " Due to a train requiring mechanical repairs at Campbelltown earlier. Please allow additional travel time.",
              "language": "en"
            }
          ]
        }
      }
    },
    {
      "id": "10",
      "alert": {
        "informed_entity": [
          {
            "agency_id": "SydneyTrains",
            "trip": {
              "trip_id": "3--P.1479.128.48.B.8.64085774"
            }
          },
          {
            "agency_id": "SydneyTrains",
            "trip": {
              "trip_id": "3--W.1479.128.48.B.8.64084519"
            }
          },
          {
            "agency_id": "SydneyTrains",
            "trip": {
              "trip_id": "3--S.1479.128.48.B.8.64085775"
            }
          },
          {
            "agency_id": "SydneyTrains",
            "trip": {
              "trip_id": "3--R.1479.128.48.B.8.64085776"
            }
          }
        ],
        "url": {
          "translation": [
            {
              "text": "https://transportnsw.info/alerts#/train",
              "language": "en"
            }
          ]
        },
        "header_text": {
          "translation": [
            {
              "text": "General update",
              "language": "en"
            }
          ]
        },
        "description_text": {
          "translation": [
            {
              "text": " The 2nd carriage is unavailable due to a mechanical issue.  Please o move along the platform to board one of the other carriages of this service.",
              "language": "en"
            }
          ]
        }
      }
    },
    {
      "id": "11",
      "alert": {
        "informed_entity": [
          {
            "agency_id": "SydneyTrains",
            "trip": {
              "trip_id": "109L.1479.128.32.T.8.64085733"
            }
          }
        ],
        "url": {
          "translation": [
            {
              "text": "https://transportnsw.info/alerts#/train",
              "language": "en"
            }
          ]
        },
        "header_text": {
          "translation": [
            {
              "text": "Now terminating at",
              "language": "en"
            }
          ]
        },
        "description_text": {
          "translation": [
            {
              "text": "North Sydney due to an operational issue earlier",
              "language": "en"
            }
          ]
        }
      }
    },
    {
      "id": "12",
      "alert": {
        "informed_entity": [
          {
            "agency_id": "SydneyTrains",
            "trip": {
              "trip_id": "109M.1479.128.32.T.8.64088345"
            }
          }
        ],
        "url": {
          "translation": [
            {
              "text": "https://transportnsw.info/alerts#/train",
              "language": "en"
            }
          ]
        },
        "header_text": {
          "translation": [
            {
              "text": "Commencing from",
              "language": "en"
            }
          ]
        },
        "description_text": {
          "translation": [
            {
              "text": "North Sydney due to an operational issue earlier",
              "language": "en"
            }
          ]
        }
      }
    },
    {
      "id": "15",
      "alert": {
        "informed_entity": [
          {
            "agency_id": "SydneyTrains",
            "trip": {
              "trip_id": "V755.1479.128.124.J.2.64089409"
            }
          }
        ],
        "url": {
          "translation": [
            {
              "text": "https://transportnsw.info/alerts#/train",
              "language": "en"
            }
          ]
        },
        "header_text": {
          "translation": [
            {
              "text": "Delayed",
              "language": "en"
            }
          ]
        },
        "description_text": {
          "translation": [
            {
              "text": " due to a slow moving freight train ahead.",
              "language": "en"
            }
          ]
        }
      }
    },
    {
      "id": "16",
      "alert": {
        "informed_entity": [
          {
            "agency_id": "SydneyTrains",
            "trip": {
              "trip_id": "20-P.1479.128.56.B.8.64086707"
            }
          },
          {
            "agency_id": "SydneyTrains",
            "trip": {
              "trip_id": "4--P.1479.128.124.B.8.64089221"
            }
          },
          {
            "agency_id": "SydneyTrains",
            "trip": {
              "trip_id": "4--R.1479.128.124.B.8.64089695"
            }
          },
          {
            "agency_id": "SydneyTrains",
            "trip": {
              "trip_id": "20-K.1479.128.56.B.8.64088304"
            }
          },
          {
            "agency_id": "SydneyTrains",
            "trip": {
              "trip_id": "20-N.1479.128.56.B.8.64084765"
            }
          }
        ],
        "url": {
          "translation": [
            {
              "text": "https://transportnsw.info/alerts#/train",
              "language": "en"
            }
          ]
        },
        "header_text": {
          "translation": [
            {
              "text": "General update",
              "language": "en"
            }
          ]
        },
        "description_text": {
          "translation": [
            {
              "text": " The 5th carriage is unavailable due to a mechanical issue.  Please move along the platform to board one of the other carriages of this service.",
              "language": "en"
            }
          ]
        }
      }
    },
    {
      "id": "22",
      "alert": {
        "informed_entity": [
          {
            "agency_id": "SydneyTrains",
            "trip": {
              "trip_id": "4--N.1479.128.124.B.8.64087135"
            }
          },
          {
            "agency_id": "SydneyTrains",
            "trip": {
              "trip_id": "4--M.1479.128.124.B.8.64087136"
            }
          },
          {
            "agency_id": "SydneyTrains",
            "trip": {
              "trip_id": "20-M.1479.128.56.B.8.64084766"
            }
          },
          {
            "agency_id": "SydneyTrains",
            "trip": {
              "trip_id": "20-L.1479.128.56.B.8.64084764"
            }
          }
        ],
        "url": {
          "translation": [
            {
              "text": "https://transportnsw.info/alerts#/train",
              "language": "en"
            }
          ]
        },
        "header_text": {
          "translation": [
            {
              "text": "General update",
              "language": "en"
            }
          ]
        },
        "description_text": {
          "translation": [
            {
              "text": " The 4th carriage is unavailable due to a mechanical issue.  Please move along the platform to board one of the other carriages of this service.",
              "language": "en"
            }
          ]
        }
      }
    },
    {
      "id": "29",
      "alert": {
        "informed_entity": [
          {
            "agency_id": "SydneyTrains",
            "trip": {
              "trip_id": "16-U.1479.128.56.B.8.64087984"
            }
          },
          {
            "agency_id": "SydneyTrains",
            "trip": {
              "trip_id": "16-T.1479.128.56.B.8.64087982"
            }
          }
        ],
        "url": {
          "translation": [
            {
              "text": "https://transportnsw.info/alerts#/train",
              "language": "en"
            }
          ]
        },
        "header_text": {
          "translation": [
            {
              "text": "General update",
              "language": "en"
            }
          ]
        },
        "description_text": {
          "translation": [
            {
              "text": " The 2nd carriage is unavailable due to a mechanical issue.  Please move along the platform to board one of the other carriages of this service.",
              "language": "en"
            }
          ]
        }
      }
    },
    {
      "id": "30",
      "alert": {
        "informed_entity": [
          {
            "agency_id": "SydneyTrains",
            "trip": {
              "trip_id": "33-F.1479.128.116.K.8.64085495"
            }
          }
        ],
        "url": {
          "translation": [
            {
              "text": "https://transportnsw.info/alerts#/train",
              "language": "en"
            }
          ]
        },
        "header_text": {
          "translation": [
            {
              "text": "Not stopping at",
              "language": "en"
            }
          ]
        },
        "description_text": {
          "translation": [
            {
              "text": "Newtown, Ashfield, Croydon, Burwood due to an operational issue earlier",
              "language": "en"
            }
          ]
        }
      }
    },
    {
      "id": "37",
      "alert": {
        "informed_entity": [
          {
            "agency_id": "SydneyTrains",
            "stop_id": "213710"
          }
        ],
        "cause": 2,
        "effect": 8,
        "url": {
          "translation": [
            {
              "text": "https://transportnsw.info/alerts#/train",
              "language": "en"
            }
          ]
        },
        "header_text": {
          "translation": [
            {
              "text": "Lift Availability - North Strathfield",
              "language": "en"
            }
          ]
        },
        "description_text": {
          "translation": [
            {
              "text": "The lift between the Concourse and Platform 3, Hamilton and Pomeroy streets is temporarily out of service. If you require assistance, please ask staff or phone 9752 8462",
              "language": "en"
            }
          ]
        }
      }
    },
    {
      "id": "38",
      "alert": {
        "informed_entity": [
          {
            "agency_id": "SydneyTrains",
            "stop_id": "221620"
          }
        ],
        "cause": 2,
        "effect": 8,
        "url": {
          "translation": [
            {
              "text": "https://transportnsw.info/alerts#/train",
              "language": "en"
            }
          ]
        },
        "header_text": {
          "translation": [
            {
              "text": "Lift Availability - Rockdale",
              "language": "en"
            }
          ]
        },
        "description_text": {
          "translation": [
            {
              "text": "The lift between the concourse and platforms 4/5 is temporarily out of service. For assistance ask staff or call 9563 7574.",
              "language": "en"
            }
          ]
        }
      }
    },
    {
      "id": "39",
      "alert": {
        "informed_entity": [
          {
            "agency_id": "SydneyTrains",
            "stop_id": "200060"
          }
        ],
        "cause": 2,
        "effect": 8,
        "url": {
          "translation": [
            {
              "text": "https://transportnsw.info/alerts#/train",
              "language": "en"
            }
          ]
        },
        "header_text": {
          "translation": [
            {
              "text": "Station Update - Central",
              "language": "en"
            }
          ]
        },
        "description_text": {
          "translation": [
            {
              "text": "There are changes happening at Central Station during Sydney Metro construction works. Access to certain areas of the station and platforms may be limited, which means using different stairs, escalators and lifts. \n\nPlease follow the signs and staff directions. If you need assistance, see station staff. \n\nFor detailed information please visit https://transportnsw.info/alerts/details#/6049959",
              "language": "en"
            }
          ]
        }
      }
    },
    {
      "id": "40",
      "alert": {
        "informed_entity": [
          {
            "agency_id": "SydneyTrains",
            "stop_id": "204420"
          }
        ],
        "cause": 2,
        "effect": 8,
        "url": {
          "translation": [
            {
              "text": "https://transportnsw.info/alerts#/train",
              "language": "en"
            }
          ]
        },
        "header_text": {
          "translation": [
            {
              "text": "Station Update - Sydenham",
              "language": "en"
            }
          ]
        },
        "description_text": {
          "translation": [
            {
              "text": "There are changes at Sydenham station during Sydney Metro construction.\n\nT3 Bankstown Line services to the City are available from platform 3 and to Lidcombe and Liverpool from platform 4.\n\nA new Metro concourse is also being constructed at the Northern end of the station. While the concourse is being installed, please board and alight from the first 5 carriages of the train on platforms 4 & 6 and the last 6 carriages of the train on platform 5.\n\nIf you need help, please see staff at the station. For more information on these upgrades, please see sydneymetro.info",
              "language": "en"
            }
          ]
        }
      }
    },
    {
      "id": "41",
      "alert": {
        "informed_entity": [
          {
            "agency_id": "SydneyTrains",
            "stop_id": "200080"
          }
        ],
        "cause": 2,
        "effect": 8,
        "url": {
          "translation": [
            {
              "text": "https://transportnsw.info/alerts#/train",
              "language": "en"
            }
          ]
        },
        "header_text": {
          "translation": [
            {
              "text": "Station Update - Wynyard",
              "language": "en"
            }
          ]
        },
        "description_text": {
          "translation": [
            {
              "text": "Due to construction works happening on a nearby building, the York Lane entry/exit to Wynyard Station will be closed from 9pm until 5am on Sunday 13, Monday 14 & Tuesday 15 December. Access to/from the station will still be available via the Clarence St & York St entry/exits. If you need assistance, see station staff.",
              "language": "en"
            }
          ]
        }
      }
    }
  ]
}